mcs/__init__.py
mcs/baseapi.py
mcs/manager.py
mcs_api-0.2.dist-info/DESCRIPTION.rst
mcs_api-0.2.dist-info/METADATA
mcs_api-0.2.dist-info/RECORD
mcs_api-0.2.dist-info/WHEEL
mcs_api-0.2.dist-info/metadata.json
mcs_api-0.2.dist-info/top_level.txt
