Metadata-Version: 2.0
Name: mcs-api
Version: 0.2
Summary: A simple Python wrapper around the Macquarie Cloud Services API
Home-page: https://bitbucket.org/AaronFoleyMT/mci-api/
Author: Aaron Foley
Author-email: afoley@macquariecloudservices.com
License: MIT
Download-URL: https://bitbucket.org/AaronFoleyMT/mci-api/get/0.1.tar.gz
Keywords: macqaurie cloud services,api
Platform: UNKNOWN
Requires-Dist: requests
